{
  "region_name": "United States - Virginia (Ashburn)",
  "google_module": {
    "base_lat": 39.0438,
    "base_lon": -77.4874,
    "lang_params": "hl=en-US&gl=US",
    "valid_url_suffix": "com"
  },
  "trust_module": {
    "white_urls": [
      "https://en.wikipedia.org/wiki/Special:Random?r=52805",
      "https://en.wikipedia.org/wiki/Special:Random?r=30105",
      "https://en.wikipedia.org/wiki/Special:Random?r=66973",
      "https://en.wikipedia.org/wiki/Special:Random?r=36770",
      "https://en.wikipedia.org/wiki/Special:Random?r=71567",
      "https://www.homedepot.com/",
      "https://en.wikipedia.org/wiki/Special:Random?r=11045",
      "https://www.usa.gov/",
      "https://en.wikipedia.org/wiki/Special:Random?r=90964",
      "https://en.wikipedia.org/wiki/Special:Random?r=21673",
      "https://en.wikipedia.org/wiki/Special:Random?r=72739",
      "https://en.wikipedia.org/wiki/Special:Random?r=18403",
      "https://en.wikipedia.org/wiki/Special:Random?r=88614",
      "https://en.wikipedia.org/wiki/Special:Random?r=32751",
      "https://en.wikipedia.org/wiki/Special:Random?r=55505",
      "https://www.irs.gov/",
      "https://en.wikipedia.org/wiki/Special:Random?r=11774",
      "https://en.wikipedia.org/wiki/Special:Random?r=46541",
      "https://en.wikipedia.org/wiki/Special:Random?r=82637",
      "https://en.wikipedia.org/wiki/Special:Random?r=29265",
      "https://en.wikipedia.org/wiki/Special:Random?r=3550",
      "https://en.wikipedia.org/wiki/Special:Random?r=14623",
      "https://en.wikipedia.org/wiki/Special:Random?r=74306",
      "https://en.wikipedia.org/wiki/Special:Random?r=39306",
      "https://en.wikipedia.org/wiki/Special:Random?r=68212",
      "https://en.wikipedia.org/wiki/Special:Random?r=79550",
      "https://www.weather.gov/",
      "https://en.wikipedia.org/wiki/Special:Random?r=26305",
      "https://en.wikipedia.org/wiki/Special:Random?r=37259",
      "https://www.chase.com/"
    ],
    "static_urls": [
      "https://www.weather.gov/",
      "https://www.irs.gov/",
      "https://www.indeed.com/",
      "https://www.zillow.com/",
      "https://www.walmart.com/",
      "https://www.homedepot.com/",
      "https://www.chase.com/",
      "https://www.usa.gov/",
      "https://www.target.com/",
      "https://www.amazon.com/"
    ]
  }
}